aiochrome/__init__.py
aiochrome/browser.py
aiochrome/cli.py
aiochrome/exceptions.py
aiochrome/tab.py
aiochrome-0.0.3.dist-info/DESCRIPTION.rst
aiochrome-0.0.3.dist-info/METADATA
aiochrome-0.0.3.dist-info/RECORD
aiochrome-0.0.3.dist-info/WHEEL
aiochrome-0.0.3.dist-info/entry_points.txt
aiochrome-0.0.3.dist-info/metadata.json
aiochrome-0.0.3.dist-info/top_level.txt
tests/__init__.py
tests/test_browser.py
tests/test_multi_tabs.py
tests/test_singile_tab.py
