Metadata-Version: 2.0
Name: aiochrome
Version: 0.0.3
Summary: UNKNOWN
Home-page: https://github.com/fate0/aiochrome
Author: fate0
Author-email: fate0@fatezero.org
License: Apache Software License 2.0
Keywords: aiochrome
Platform: UNKNOWN
Classifier: Development Status :: 5 - Production/Stable
Classifier: Intended Audience :: Developers
Classifier: License :: OSI Approved :: Apache Software License
Classifier: Natural Language :: English
Classifier: Programming Language :: Python :: 3.5
Classifier: Programming Language :: Python :: 3.6
Requires-Dist: aiohttp (>=2.2.5)
Requires-Dist: websockets (>=3.4)
